dict_field_redacter/__init__.py
dict_field_redacter/main.py
dict_field_redacter/models.py
dict_field_redacter/test.py
dict_field_redacter/utils.py
dict_field_redacter-0.1.3.dist-info/licenses/LICENCE.md
dict_field_redacter-0.1.3.dist-info/METADATA
dict_field_redacter-0.1.3.dist-info/WHEEL
dict_field_redacter-0.1.3.dist-info/top_level.txt
dict_field_redacter-0.1.3.dist-info/RECORD
