Metadata-Version: 2.4
Name: dict_field_redacter
Version: 0.1.3
Summary: dict-field-redacter: A utility to redact sensitive fields in dictionaries. Easily sanitize your data by masking fields like passwords, tokens, secrets and more... Good for Log Sanitization, Data Privacy, and Security.
Home-page: https://github.com/ilemlembo/dict-field-redacter
Author: LEMBO Ilem Nelson
Author-email: lemboilem@lembo.com
Classifier: Programming Language :: Python :: 3
Classifier: License :: OSI Approved :: MIT License
Classifier: Operating System :: OS Independent
Classifier: Development Status :: 5 - Production/Stable
Classifier: Intended Audience :: Developers
Classifier: Intended Audience :: System Administrators
Classifier: Intended Audience :: Information Technology
Requires-Python: >=3.6
License-File: LICENCE.md
Dynamic: author
Dynamic: author-email
Dynamic: classifier
Dynamic: description
Dynamic: description-content-type
Dynamic: home-page
Dynamic: license-file
Dynamic: requires-python
Dynamic: summary
